RISC-V/ALU.v
module ALU(A,B,Result,ALUControl,OverFlow,Carry,Zero,Negative);

    input [31:0]A,B;                // 32-bit input operands
    input [2:0]ALUControl;          // 3-bit control signal to select ALU operation
    output Carry,OverFlow,Zero,Negative; // Status flags
    output [31:0]Result;            // 32-bit ALU result

    wire Cout;                      // Carry out from addition/subtraction
    wire [31:0]Sum;                 // Sum result from addition/subtraction

    // Perform addition or subtraction based on ALUControl[0]
    // If ALUControl[0] == 0: A + B
    // If ALUControl[0] == 1: A + (~B + 1) (i.e., A - B)
    assign {Cout,Sum} = (ALUControl[0] == 1'b0) ? A + B :
                                          (A + ((~B)+1)) ;
  
    // Select ALU operation based on ALUControl
    // 000: ADD, 001: SUB, 010: AND, 011: OR, 101: SLT (set less than)
    assign Result = (ALUControl == 3'b000) ? Sum :
                    (ALUControl == 3'b001) ? Sum :
                    (ALUControl == 3'b010) ? A & B :
                    (ALUControl == 3'b011) ? A | B :
                    (ALUControl == 3'b101) ? {{31{1'b0}},(Sum[31])} : {32{1'b0}};
    
    // Overflow detection for addition/subtraction
    assign OverFlow = ((Sum[31] ^ A[31]) & 
                      (~(ALUControl[0] ^ B[31] ^ A[31])) &
                      (~ALUControl[1]));

    // Carry flag for addition/subtraction
    assign Carry = ((~ALUControl[1]) & Cout);

    // Zero flag: set if Result is zero
    assign Zero = &(~Result);

    // Negative flag: set if Result is negative (MSB is 1)
    assign Negative = Result[31];

endmodule

RISC-V/ALU_tb.v
`timescale 1ns/1ps

module ALU_tb;
    // Inputs
    reg [31:0] A, B;
    reg [2:0] ALUControl;
    
    // Outputs
    wire [31:0] Result;
    wire OverFlow, Carry, Zero, Negative;
    
    // Instantiate the ALU
    ALU uut (
        .A(A),
        .B(B),
        .Result(Result),
        .ALUControl(ALUControl),
        .OverFlow(OverFlow),
        .Carry(Carry),
        .Zero(Zero),
        .Negative(Negative)
    );
    
    // Initialize dump
    initial begin
        $dumpfile("ALU_waveforms.vcd");
        $dumpvars(0, ALU_tb);
    end
    
    // Test cases
    initial begin
        // Test ADD (000)
        ALUControl = 3'b000;
        A = 32'h00000005;
        B = 32'h00000003;
        #10;
        
        // Test SUB (001)
        ALUControl = 3'b001;
        A = 32'h00000007;
        B = 32'h00000002;
        #10;
        
        // Test AND (010)
        ALUControl = 3'b010;
        A = 32'hF0F0F0F0;
        B = 32'h0F0F0F0F;
        #10;
        
        // Test OR (011)
        ALUControl = 3'b011;
        A = 32'hAAAAAAAA;
        B = 32'h55555555;
        #10;
        
        // Test SLT (101)
        ALUControl = 3'b101;
        A = 32'h00000001;
        B = 32'h00000002;
        #10;
        
        A = 32'hFFFFFFFE;  // -2
        B = 32'hFFFFFFFF;  // -1
        #10;
        
        // Test overflow cases
        ALUControl = 3'b000;  // ADD
        A = 32'h7FFFFFFF;  // Max positive
        B = 32'h00000001;
        #10;
        
        ALUControl = 3'b001;  // SUB
        A = 32'h80000000;  // Min negative
        B = 32'h00000001;
        #10;
        
        $display("Simulation complete. Waveform saved to ALU_waveforms.vcd");
        $finish;
    end
    
    // Monitor changes
    initial begin
        $monitor("Time = %t: A=%h B=%h ALUControl=%b Result=%h Overflow=%b Carry=%b Zero=%b Negative=%b",
                 $time, A, B, ALUControl, Result, OverFlow, Carry, Zero, Negative);
    end
endmodule

RISC-V/Waveforms/ALU_waveforms.vcd
$date
	Fri Jun 27 01:47:55 2025
$end
$version
	Icarus Verilog
$end
$timescale
	1ps
$end
$scope module ALU_tb $end
$var wire 1 ! Zero $end
$var wire 32 " Result [31:0] $end
$var wire 1 # OverFlow $end
$var wire 1 $ Negative $end
$var wire 1 % Carry $end
$var reg 32 & A [31:0] $end
$var reg 3 ' ALUControl [2:0] $end
$var reg 32 ( B [31:0] $end
$scope module uut $end
$var wire 32 ) A [31:0] $end
$var wire 3 * ALUControl [2:0] $end
$var wire 32 + B [31:0] $end
$var wire 1 % Carry $end
$var wire 1 # OverFlow $end
$var wire 1 ! Zero $end
$var wire 32 , Sum [31:0] $end
$var wire 32 - Result [31:0] $end
$var wire 1 $ Negative $end
$var wire 1 . Cout $end
$upscope $end
$upscope $end
$enddefinitions $end
$comment Show the parameter values. $end
$dumpall
$end
#0
$dumpvars
0.
b1000 -
b1000 ,
b11 +
b0 *
b101 )
b11 (
b0 '
b101 &
0%
0$
0#
b1000 "
0!
$end
#10000
b101 "
b101 -
b101 ,
b10 (
b10 +
b111 &
b111 )
b1 '
b1 *
#20000
1!
b11111111111111111111111111111111 ,
b0 "
b0 -
b1111000011110000111100001111 (
b1111000011110000111100001111 +
b11110000111100001111000011110000 &
b11110000111100001111000011110000 )
b10 '
b10 *
#30000
b1010101010101010101010101010101 ,
1$
0!
b11111111111111111111111111111111 "
b11111111111111111111111111111111 -
b1010101010101010101010101010101 (
b1010101010101010101010101010101 +
b10101010101010101010101010101010 &
b10101010101010101010101010101010 )
b11 '
b11 *
#40000
0$
0!
b1 "
b1 -
0#
1%
b11111111111111111111111111111111 ,
1.
b10 (
b10 +
b1 &
b1 )
b101 '
b101 *
#50000
1%
b11111111111111111111111111111111 ,
1.
b11111111111111111111111111111111 (
b11111111111111111111111111111111 +
b11111111111111111111111111111110 &
b11111111111111111111111111111110 )
#60000
0%
1#
0.
b10000000000000000000000000000000 ,
1$
b10000000000000000000000000000000 "
b10000000000000000000000000000000 -
b1 (
b1 +
b1111111111111111111111111111111 &
b1111111111111111111111111111111 )
b0 '
b0 *
#70000
0$
b1111111111111111111111111111111 "
b1111111111111111111111111111111 -
1#
b1111111111111111111111111111111 ,
b10000000000000000000000000000000 &
b10000000000000000000000000000000 )
b1 '
b1 *
